ps_pessoas_fastapi_lib/__init__.py
ps_pessoas_fastapi_lib/model/__init__.py
ps_pessoas_fastapi_lib/model/dto.py
ps_pessoas_fastapi_lib/model/models.py
ps_pessoas_fastapi_lib/repository/__init__.py
ps_pessoas_fastapi_lib/repository/base.py
ps_pessoas_fastapi_lib/service/__init__.py
ps_pessoas_fastapi_lib/service/base.py
ps_pessoas_fastapi_lib/util/__init__.py
ps_pessoas_fastapi_lib/util/database.py
ps_pessoas_fastapi_lib-0.1.3.dist-info/licenses/LICENSE
ps_pessoas_fastapi_lib-0.1.3.dist-info/METADATA
ps_pessoas_fastapi_lib-0.1.3.dist-info/WHEEL
ps_pessoas_fastapi_lib-0.1.3.dist-info/top_level.txt
ps_pessoas_fastapi_lib-0.1.3.dist-info/RECORD
